armr_forge/__init__.py
armr_forge/armr_forge.py
armr_forge-0.1.19.dist-info/LICENSE_PYTHON.txt
armr_forge-0.1.19.dist-info/METADATA
armr_forge-0.1.19.dist-info/WHEEL
armr_forge-0.1.19.dist-info/top_level.txt
armr_forge-0.1.19.dist-info/RECORD
