Metadata-Version: 2.1
Name: armr-forge
Version: 0.1.19
Summary: The Adanced Record Management Resource
Home-page: https://github.com/StalwartBI/armr_forge/armr_forge
Author: StalwartBI
Author-email: StalwartBI@outlook.com
License: Apache License 2.0
License-File: LICENSE_PYTHON.txt
Requires-Dist: bcrypt >=4.0.1
Requires-Dist: cryptography >=41.0.5
Requires-Dist: numpy >=1.26.1
Requires-Dist: pandas >=2.1.2
